doge/__init__.py
doge/core.py
doge/wow.py
doge/static/doge-halloween.txt
doge/static/doge-small.txt
doge/static/doge-thanksgiving.txt
doge/static/doge-xmas.txt
doge/static/doge.txt
doge_art-3.7.3.dist-info/LICENSE
doge_art-3.7.3.dist-info/METADATA
doge_art-3.7.3.dist-info/WHEEL
doge_art-3.7.3.dist-info/entry_points.txt
doge_art-3.7.3.dist-info/top_level.txt
doge_art-3.7.3.dist-info/RECORD
